pyccu3/__init__.py
pyccu3/constants.py
pyccu3/enums.py
pyccu3/objects/__init__.py
pyccu3/objects/base.py
pyccu3/objects/legacy.py
pyccu3/objects/xml_api.py
pyccu3/types.py
pyccu3-0.0.5.dist-info/LICENSE
pyccu3-0.0.5.dist-info/METADATA
pyccu3-0.0.5.dist-info/WHEEL
pyccu3-0.0.5.dist-info/RECORD
