Metadata-Version: 2.3
Name: pyccu3
Version: 0.0.5
Summary: 
License: MIT
Author: Cellebyte
Author-email: marcel.fest@live.de
Requires-Python: >=3.10
Classifier: License :: OSI Approved :: MIT License
Classifier: Programming Language :: Python :: 3
Classifier: Programming Language :: Python :: 3.10
Classifier: Programming Language :: Python :: 3.11
Classifier: Programming Language :: Python :: 3.12
Classifier: Programming Language :: Python :: 3.13
Requires-Dist: dacite (>=1.8.1,<2.0.0)
Requires-Dist: json-fix (>=0.5.2,<0.6.0)
Requires-Dist: requests (>=2.31.0,<3.0.0)
Requires-Dist: xmltodict (>=0.13.0,<0.14.0)
